Metadata-Version: 2.4
Name: post-si
Version: 0.1.0
Home-page: https://github.com/PythonSI/PSI
Author: Tran Tuan Kiet, Nguyen Thang Loi, Duong Tan Loc, Vo Nguyen Le Duy, PSI Contributors
Author-email: contact.trtkiet@gmail.com; duyvnl@uit.edu.vn
Requires-Python: >=3.10
License-File: LICENSE
Requires-Dist: mpmath==1.3.0
Requires-Dist: numpy==2.2.6
Requires-Dist: POT==0.9.5
Requires-Dist: scikit-learn==1.7.1
Requires-Dist: scipy==1.15.3
Dynamic: author
Dynamic: author-email
Dynamic: description
Dynamic: description-content-type
Dynamic: home-page
Dynamic: license-file
Dynamic: requires-dist
Dynamic: requires-python
